FAImageGen/__init__.py
FAImageGen/api_client.py
FAImageGen/fuzer.py
FAImageGen/harmonizer.py
FAImageGen/image_generation.py
InstantLight/__init__.py
InstantLight/api_client.py
InstantLight/image_generation.py
fai_gensdk-0.1.8.dist-info/LICENSE
fai_gensdk-0.1.8.dist-info/METADATA
fai_gensdk-0.1.8.dist-info/WHEEL
fai_gensdk-0.1.8.dist-info/top_level.txt
fai_gensdk-0.1.8.dist-info/RECORD
